makenew_serverless_python/__init__.py
makenew_serverless_python/todo.py
makenew_serverless_python/todo_test.py
makenew_serverless_python-6.6.0.dist-info/LICENSE.txt
makenew_serverless_python-6.6.0.dist-info/WHEEL
makenew_serverless_python-6.6.0.dist-info/METADATA
makenew_serverless_python-6.6.0.dist-info/RECORD
