Metadata-Version: 2.1
Name: makenew-serverless-python
Version: 6.6.0
Summary: Package skeleton for a Python Serverless project on AWS Lambda.
Home-page: https://github.com/makenew/serverless-python
License: MIT
Author: Evan Sosenko
Author-email: razorx@evansosenko.com
Requires-Python: >=3.9.14,<4.0.0
Classifier: License :: OSI Approved :: MIT License
Classifier: Programming Language :: Python :: 3
Classifier: Programming Language :: Python :: 3.10
Requires-Dist: toml (>=0.10.2,<0.11.0)
Project-URL: Repository, https://github.com/makenew/serverless-python
